{"kind":"interface","name":"ServiceWorker","inherits":"EventTarget","extended_attributes":["ActiveScriptWrappable","Exposed(Window StableBlinkFeatures, ServiceWorker StableBlinkFeatures, DedicatedWorker ServiceWorkerInDedicatedWorker)","Exposed=(Window, Worker)","SecureContext"],"members":[{"kind":"attribute","name":"onerror","type_":"EventHandler","arguments":[],"modifiers":[],"extended_attributes":[]},{"kind":"attribute","name":"onstatechange","type_":"EventHandler","arguments":[],"modifiers":[],"extended_attributes":[]},{"kind":"attribute","name":"scriptURL","type_":"USVString","arguments":[],"modifiers":["readonly"],"extended_attributes":[]},{"kind":"attribute","name":"state","type_":"ServiceWorkerState","arguments":[],"modifiers":["readonly"],"extended_attributes":[]},{"kind":"operation","name":"postMessage","type_":"void","arguments":[{"name":"message","type_":"any","optional":false,"variadic":false,"extended_attributes":[]},{"name":"options","type_":"PostMessageOptions","optional":true,"variadic":false,"default":"{}","extended_attributes":[]}],"modifiers":[],"extended_attributes":["CallWith=ScriptState","RaisesException"]},{"kind":"operation","name":"postMessage","type_":"void","arguments":[{"name":"message","type_":"any","optional":false,"variadic":false,"extended_attributes":[]},{"name":"transfer","type_":"sequence<object>","optional":false,"variadic":false,"extended_attributes":[]}],"modifiers":[],"extended_attributes":["CallWith=ScriptState","RaisesException"]}]}