{"kind":"interface","name":"CommandEvent","inherits":"Event","extended_attributes":["Exposed=Window","RuntimeEnabled=HTMLInvokeTargetAttribute"],"members":[{"kind":"attribute","name":"command","type_":"DOMString","arguments":[],"modifiers":["readonly"],"extended_attributes":[]},{"kind":"attribute","name":"invoker","type_":"Element?","arguments":[],"modifiers":["readonly"],"extended_attributes":[]},{"kind":"constructor","name":"","arguments":[{"name":"type","type_":"DOMString","optional":false,"variadic":false,"extended_attributes":[]},{"name":"eventInitDict","type_":"CommandEventInit","optional":true,"variadic":false,"default":"{}","extended_attributes":[]}],"modifiers":[],"extended_attributes":[]}]}