{"kind":"interface","name":"Gamepad","extended_attributes":["Exposed=Window"],"members":[{"kind":"attribute","name":"axes","type_":"FrozenArray<double>","arguments":[],"modifiers":["readonly"],"extended_attributes":["CachedAttribute=isAxisDataDirty","MeasureAs=GamepadAxes"]},{"kind":"attribute","name":"buttons","type_":"FrozenArray<GamepadButton>","arguments":[],"modifiers":["readonly"],"extended_attributes":["CachedAttribute=isButtonDataDirty","MeasureAs=GamepadButtons"]},{"kind":"attribute","name":"connected","type_":"boolean","arguments":[],"modifiers":["readonly"],"extended_attributes":[]},{"kind":"attribute","name":"id","type_":"DOMString","arguments":[],"modifiers":["readonly"],"extended_attributes":["HighEntropy=Direct","MeasureAs=GamepadId"]},{"kind":"attribute","name":"index","type_":"long","arguments":[],"modifiers":["readonly"],"extended_attributes":[]},{"kind":"attribute","name":"mapping","type_":"GamepadMappingType","arguments":[],"modifiers":["readonly"],"extended_attributes":[]},{"kind":"attribute","name":"timestamp","type_":"DOMHighResTimeStamp","arguments":[],"modifiers":["readonly"],"extended_attributes":[]},{"kind":"attribute","name":"vibrationActuator","type_":"GamepadHapticActuator?","arguments":[],"modifiers":["readonly"],"extended_attributes":["MeasureAs=GamepadVibrationActuator"]}]}