{"kind":"interface","name":"RTCRtpTransceiver","extended_attributes":["Exposed=Window","Pref=\"media.peerconnection.enabled\""],"members":[{"kind":"attribute","name":"currentDirection","type_":"RTCRtpTransceiverDirection?","arguments":[],"modifiers":["readonly"],"extended_attributes":[]},{"kind":"attribute","name":"direction","type_":"RTCRtpTransceiverDirection","arguments":[],"modifiers":[],"extended_attributes":["SetterThrows"]},{"kind":"attribute","name":"mid","type_":"DOMString?","arguments":[],"modifiers":["readonly"],"extended_attributes":[]},{"kind":"attribute","name":"receiver","type_":"RTCRtpReceiver","arguments":[],"modifiers":["readonly"],"extended_attributes":["SameObject"]},{"kind":"attribute","name":"sender","type_":"RTCRtpSender","arguments":[],"modifiers":["readonly"],"extended_attributes":["SameObject"]},{"kind":"attribute","name":"stopped","type_":"boolean","arguments":[],"modifiers":["readonly"],"extended_attributes":[]},{"kind":"operation","name":"getKind","type_":"DOMString","arguments":[],"modifiers":[],"extended_attributes":["ChromeOnly"]},{"kind":"operation","name":"hasBeenUsedToSend","type_":"boolean","arguments":[],"modifiers":[],"extended_attributes":["ChromeOnly"]},{"kind":"operation","name":"setDirectionInternal","type_":"undefined","arguments":[{"name":"direction","type_":"RTCRtpTransceiverDirection","optional":false,"variadic":false,"extended_attributes":[]}],"modifiers":[],"extended_attributes":["ChromeOnly"]},{"kind":"operation","name":"stop","type_":"undefined","arguments":[],"modifiers":[],"extended_attributes":["Throws"]}]}