{"kind":"interface","name":"AccessibleNode","inherits":"EventTarget","extended_attributes":["Exposed=Window","RuntimeEnabled=AccessibilityObjectModel"],"members":[{"kind":"attribute","name":"activeDescendant","type_":"AccessibleNode?","arguments":[],"modifiers":[],"extended_attributes":[]},{"kind":"attribute","name":"atomic","type_":"boolean?","arguments":[],"modifiers":[],"extended_attributes":[]},{"kind":"attribute","name":"autocomplete","type_":"DOMString?","arguments":[],"modifiers":[],"extended_attributes":[]},{"kind":"attribute","name":"busy","type_":"boolean?","arguments":[],"modifiers":[],"extended_attributes":[]},{"kind":"attribute","name":"checked","type_":"DOMString?","arguments":[],"modifiers":[],"extended_attributes":[]},{"kind":"attribute","name":"childNodes","type_":"AccessibleNodeList","arguments":[],"modifiers":["readonly"],"extended_attributes":[]},{"kind":"attribute","name":"colCount","type_":"long?","arguments":[],"modifiers":[],"extended_attributes":[]},{"kind":"attribute","name":"colIndex","type_":"unsigned long?","arguments":[],"modifiers":[],"extended_attributes":[]},{"kind":"attribute","name":"colSpan","type_":"unsigned long?","arguments":[],"modifiers":[],"extended_attributes":[]},{"kind":"attribute","name":"controls","type_":"AccessibleNodeList?","arguments":[],"modifiers":[],"extended_attributes":[]},{"kind":"attribute","name":"current","type_":"DOMString?","arguments":[],"modifiers":[],"extended_attributes":[]},{"kind":"attribute","name":"describedBy","type_":"AccessibleNodeList?","arguments":[],"modifiers":[],"extended_attributes":[]},{"kind":"attribute","name":"details","type_":"AccessibleNodeList?","arguments":[],"modifiers":[],"extended_attributes":[]},{"kind":"attribute","name":"disabled","type_":"boolean?","arguments":[],"modifiers":[],"extended_attributes":[]},{"kind":"attribute","name":"errorMessage","type_":"AccessibleNode?","arguments":[],"modifiers":[],"extended_attributes":[]},{"kind":"attribute","name":"expanded","type_":"boolean?","arguments":[],"modifiers":[],"extended_attributes":[]},{"kind":"attribute","name":"flowTo","type_":"AccessibleNodeList?","arguments":[],"modifiers":[],"extended_attributes":[]},{"kind":"attribute","name":"hasPopUp","type_":"DOMString?","arguments":[],"modifiers":[],"extended_attributes":[]},{"kind":"attribute","name":"hidden","type_":"boolean?","arguments":[],"modifiers":[],"extended_attributes":[]},{"kind":"attribute","name":"invalid","type_":"DOMString?","arguments":[],"modifiers":[],"extended_attributes":[]},{"kind":"attribute","name":"keyShortcuts","type_":"DOMString?","arguments":[],"modifiers":[],"extended_attributes":[]},{"kind":"attribute","name":"label","type_":"DOMString?","arguments":[],"modifiers":[],"extended_attributes":[]},{"kind":"attribute","name":"labeledBy","type_":"AccessibleNodeList?","arguments":[],"modifiers":[],"extended_attributes":[]},{"kind":"attribute","name":"level","type_":"unsigned long?","arguments":[],"modifiers":[],"extended_attributes":[]},{"kind":"attribute","name":"live","type_":"DOMString?","arguments":[],"modifiers":[],"extended_attributes":[]},{"kind":"attribute","name":"modal","type_":"boolean?","arguments":[],"modifiers":[],"extended_attributes":[]},{"kind":"attribute","name":"multiline","type_":"boolean?","arguments":[],"modifiers":[],"extended_attributes":[]},{"kind":"attribute","name":"multiselectable","type_":"boolean?","arguments":[],"modifiers":[],"extended_attributes":[]},{"kind":"attribute","name":"onaccessibleclick","type_":"EventHandler","arguments":[],"modifiers":[],"extended_attributes":[]},{"kind":"attribute","name":"onaccessiblecontextmenu","type_":"EventHandler","arguments":[],"modifiers":[],"extended_attributes":[]},{"kind":"attribute","name":"onaccessibledecrement","type_":"EventHandler","arguments":[],"modifiers":[],"extended_attributes":[]},{"kind":"attribute","name":"onaccessiblefocus","type_":"EventHandler","arguments":[],"modifiers":[],"extended_attributes":[]},{"kind":"attribute","name":"onaccessibleincrement","type_":"EventHandler","arguments":[],"modifiers":[],"extended_attributes":[]},{"kind":"attribute","name":"onaccessiblescrollintoview","type_":"EventHandler","arguments":[],"modifiers":[],"extended_attributes":[]},{"kind":"attribute","name":"orientation","type_":"DOMString?","arguments":[],"modifiers":[],"extended_attributes":[]},{"kind":"attribute","name":"owns","type_":"AccessibleNodeList?","arguments":[],"modifiers":[],"extended_attributes":[]},{"kind":"attribute","name":"placeholder","type_":"DOMString?","arguments":[],"modifiers":[],"extended_attributes":[]},{"kind":"attribute","name":"posInSet","type_":"unsigned long?","arguments":[],"modifiers":[],"extended_attributes":[]},{"kind":"attribute","name":"pressed","type_":"DOMString?","arguments":[],"modifiers":[],"extended_attributes":[]},{"kind":"attribute","name":"readOnly","type_":"boolean?","arguments":[],"modifiers":[],"extended_attributes":[]},{"kind":"attribute","name":"relevant","type_":"DOMString?","arguments":[],"modifiers":[],"extended_attributes":[]},{"kind":"attribute","name":"required","type_":"boolean?","arguments":[],"modifiers":[],"extended_attributes":[]},{"kind":"attribute","name":"role","type_":"DOMString?","arguments":[],"modifiers":[],"extended_attributes":[]},{"kind":"attribute","name":"roleDescription","type_":"DOMString?","arguments":[],"modifiers":[],"extended_attributes":[]},{"kind":"attribute","name":"rowCount","type_":"long?","arguments":[],"modifiers":[],"extended_attributes":[]},{"kind":"attribute","name":"rowIndex","type_":"unsigned long?","arguments":[],"modifiers":[],"extended_attributes":[]},{"kind":"attribute","name":"rowSpan","type_":"unsigned long?","arguments":[],"modifiers":[],"extended_attributes":[]},{"kind":"attribute","name":"selected","type_":"boolean?","arguments":[],"modifiers":[],"extended_attributes":[]},{"kind":"attribute","name":"setSize","type_":"long?","arguments":[],"modifiers":[],"extended_attributes":[]},{"kind":"attribute","name":"sort","type_":"DOMString?","arguments":[],"modifiers":[],"extended_attributes":[]},{"kind":"attribute","name":"valueMax","type_":"double?","arguments":[],"modifiers":[],"extended_attributes":[]},{"kind":"attribute","name":"valueMin","type_":"double?","arguments":[],"modifiers":[],"extended_attributes":[]},{"kind":"attribute","name":"valueNow","type_":"double?","arguments":[],"modifiers":[],"extended_attributes":[]},{"kind":"attribute","name":"valueText","type_":"DOMString?","arguments":[],"modifiers":[],"extended_attributes":[]},{"kind":"constructor","name":"","arguments":[],"modifiers":[],"extended_attributes":["CallWith=Document"]},{"kind":"operation","name":"appendChild","type_":"void","arguments":[{"name":"child","type_":"AccessibleNode","optional":false,"variadic":false,"extended_attributes":[]}],"modifiers":[],"extended_attributes":["RaisesException"]},{"kind":"operation","name":"removeChild","type_":"void","arguments":[{"name":"child","type_":"AccessibleNode","optional":false,"variadic":false,"extended_attributes":[]}],"modifiers":[],"extended_attributes":["RaisesException"]}]}