{"kind":"interface","name":"XRInputSourceEvent","inherits":"Event","extended_attributes":["Conditional=WEBXR","EnabledBySetting=WebXR","Exposed=Window","SecureContext"],"members":[{"kind":"attribute","name":"frame","type_":"WebXRFrame","arguments":[],"modifiers":["readonly"],"extended_attributes":["SameObject"]},{"kind":"attribute","name":"inputSource","type_":"WebXRInputSource","arguments":[],"modifiers":["readonly"],"extended_attributes":["SameObject"]},{"kind":"constructor","name":"","arguments":[{"name":"type","type_":"DOMString","optional":false,"variadic":false,"extended_attributes":[]},{"name":"eventInitDict","type_":"XRInputSourceEventInit","optional":false,"variadic":false,"extended_attributes":[]}],"modifiers":[],"extended_attributes":[]}]}