{"kind":"interface","name":"DelegatedInkTrailPresenter","extended_attributes":["Exposed=Window"],"members":[{"kind":"attribute","name":"presentationArea","type_":"Element?","arguments":[],"modifiers":["readonly"],"extended_attributes":[]},{"kind":"operation","name":"updateInkTrailStartPoint","type_":"void","arguments":[{"name":"evt","type_":"PointerEvent","optional":false,"variadic":false,"extended_attributes":[]},{"name":"style","type_":"InkTrailStyle","optional":false,"variadic":false,"extended_attributes":[]}],"modifiers":[],"extended_attributes":["CallWith=ScriptState","RaisesException"]}]}