{"kind":"interface","name":"WebGLGetBufferSubDataAsync","extended_attributes":["DoNotCheckConstants","NoInterfaceObject"],"members":[{"kind":"operation","name":"getBufferSubDataAsync","type_":"Promise<ArrayBufferView>","arguments":[{"name":"target","type_":"GLenum","optional":false,"variadic":false,"extended_attributes":[]},{"name":"srcByteOffset","type_":"GLintptr","optional":false,"variadic":false,"extended_attributes":[]},{"name":"dstData","type_":"ArrayBufferView","optional":false,"variadic":false,"extended_attributes":[]},{"name":"dstOffset","type_":"GLuint","optional":true,"variadic":false,"default":"0","extended_attributes":[]},{"name":"length","type_":"GLuint","optional":true,"variadic":false,"default":"0","extended_attributes":[]}],"modifiers":[],"extended_attributes":["CallWith=ScriptState"]}]}