{"kind":"dictionary","name":"VideoFrameInit","extended_attributes":["Conditional=WEB_CODECS"],"fields":[{"name":"alpha","type_":"WebCodecsAlphaOption","required":false,"extended_attributes":[]},{"name":"displayHeight","type_":"unsigned long","required":false,"extended_attributes":["EnforceRange"]},{"name":"displayWidth","type_":"unsigned long","required":false,"extended_attributes":["EnforceRange"]},{"name":"duration","type_":"unsigned long long","required":false,"extended_attributes":[]},{"name":"timestamp","type_":"long long","required":false,"extended_attributes":[]},{"name":"visibleRect","type_":"DOMRectInit","required":false,"extended_attributes":[]}]}