{"kind":"interface","name":"WebGLProvokingVertex","extended_attributes":["Conditional=WEBGL","GenerateIsReachable","LegacyNoInterfaceObject"],"members":[{"kind":"const","name":"FIRST_VERTEX_CONVENTION_WEBGL","type_":"unsigned long","arguments":[],"modifiers":[],"value":"0x8E4D","extended_attributes":[]},{"kind":"const","name":"LAST_VERTEX_CONVENTION_WEBGL","type_":"unsigned long","arguments":[],"modifiers":[],"value":"0x8E4E","extended_attributes":[]},{"kind":"const","name":"PROVOKING_VERTEX_WEBGL","type_":"unsigned long","arguments":[],"modifiers":[],"value":"0x8E4F","extended_attributes":[]},{"kind":"operation","name":"provokingVertexWEBGL","type_":"undefined","arguments":[{"name":"provokeMode","type_":"unsigned long","optional":false,"variadic":false,"extended_attributes":[]}],"modifiers":[],"extended_attributes":[]}]}