{"kind":"interface","name":"ImageCaptureError","extended_attributes":["Exposed=Window","NoInterfaceObject"],"members":[{"kind":"const","name":"ERROR_UNKNOWN","type_":"unsigned short","arguments":[],"modifiers":[],"value":"4","extended_attributes":[]},{"kind":"const","name":"FRAME_GRAB_ERROR","type_":"unsigned short","arguments":[],"modifiers":[],"value":"1","extended_attributes":[]},{"kind":"const","name":"PHOTO_ERROR","type_":"unsigned short","arguments":[],"modifiers":[],"value":"3","extended_attributes":[]},{"kind":"const","name":"SETTINGS_ERROR","type_":"unsigned short","arguments":[],"modifiers":[],"value":"2","extended_attributes":[]},{"kind":"attribute","name":"code","type_":"unsigned short","arguments":[],"modifiers":["readonly"],"extended_attributes":[]},{"kind":"attribute","name":"message","type_":"DOMString","arguments":[],"modifiers":["readonly"],"extended_attributes":[]}]}