{"kind":"interface","name":"FederatedCredential","inherits":"Credential","extended_attributes":["Exposed=Window","SecureContext"],"members":[{"kind":"attribute","name":"approvedBy","type_":"FederatedCredentialApprover","arguments":[],"modifiers":["readonly"],"extended_attributes":["RuntimeEnabled=WebID"]},{"kind":"attribute","name":"iconURL","type_":"USVString","arguments":[],"modifiers":["readonly"],"extended_attributes":[]},{"kind":"attribute","name":"idToken","type_":"USVString","arguments":[],"modifiers":["readonly"],"extended_attributes":["RuntimeEnabled=WebID"]},{"kind":"attribute","name":"name","type_":"USVString","arguments":[],"modifiers":["readonly"],"extended_attributes":[]},{"kind":"attribute","name":"protocol","type_":"DOMString?","arguments":[],"modifiers":["readonly"],"extended_attributes":[]},{"kind":"attribute","name":"provider","type_":"USVString","arguments":[],"modifiers":["readonly"],"extended_attributes":[]},{"kind":"constructor","name":"","arguments":[{"name":"data","type_":"FederatedCredentialInit","optional":false,"variadic":false,"extended_attributes":[]}],"modifiers":[],"extended_attributes":["RaisesException"]},{"kind":"operation","name":"logoutRps","type_":"Promise<void>","arguments":[{"name":"logout_requests","type_":"sequence<FederatedCredentialLogoutRpsRequest>","optional":true,"variadic":false,"default":"[]","extended_attributes":[]}],"modifiers":["static"],"extended_attributes":["RuntimeEnabled=WebID","CallWith=ScriptState"]},{"kind":"operation","name":"revoke","type_":"Promise<void>","arguments":[{"name":"account_id","type_":"USVString","optional":false,"variadic":false,"extended_attributes":[]},{"name":"provider","type_":"FederatedIdentityProvider","optional":false,"variadic":false,"extended_attributes":[]}],"modifiers":["static"],"extended_attributes":["RuntimeEnabled=WebID","CallWith=ScriptState","RaisesException"]}]}