{"kind":"interface","name":"RTCRtpSendStream","extended_attributes":["Exposed=(Window, Worker)","RuntimeEnabled=RTCRtpTransport"],"members":[{"kind":"operation","name":"sendRtp","type_":"Promise<RTCRtpSendResult>","arguments":[{"name":"packet","type_":"RTCRtpPacketInit","optional":false,"variadic":false,"extended_attributes":[]},{"name":"options","type_":"RTCRtpSendOptions","optional":false,"variadic":false,"extended_attributes":[]}],"modifiers":[],"extended_attributes":["CallWith=ScriptState"]}]}