{"kind":"interface","name":"PeerConnectionImpl","extended_attributes":["ChromeOnly","Exposed=Window"],"members":[{"kind":"attribute","name":"certificate","type_":"RTCCertificate","arguments":[],"modifiers":[],"extended_attributes":[]},{"kind":"attribute","name":"connectionState","type_":"RTCPeerConnectionState","arguments":[],"modifiers":["readonly"],"extended_attributes":[]},{"kind":"attribute","name":"currentLocalDescription","type_":"DOMString","arguments":[],"modifiers":["readonly"],"extended_attributes":[]},{"kind":"attribute","name":"currentOfferer","type_":"boolean?","arguments":[],"modifiers":["readonly"],"extended_attributes":[]},{"kind":"attribute","name":"currentRemoteDescription","type_":"DOMString","arguments":[],"modifiers":["readonly"],"extended_attributes":[]},{"kind":"attribute","name":"fingerprint","type_":"DOMString","arguments":[],"modifiers":["readonly"],"extended_attributes":["Constant"]},{"kind":"attribute","name":"iceConnectionState","type_":"RTCIceConnectionState","arguments":[],"modifiers":["readonly"],"extended_attributes":[]},{"kind":"attribute","name":"iceGatheringState","type_":"RTCIceGatheringState","arguments":[],"modifiers":["readonly"],"extended_attributes":[]},{"kind":"attribute","name":"id","type_":"DOMString","arguments":[],"modifiers":[],"extended_attributes":[]},{"kind":"attribute","name":"peerIdentity","type_":"DOMString","arguments":[],"modifiers":[],"extended_attributes":["SetterThrows"]},{"kind":"attribute","name":"pendingLocalDescription","type_":"DOMString","arguments":[],"modifiers":["readonly"],"extended_attributes":[]},{"kind":"attribute","name":"pendingOfferer","type_":"boolean?","arguments":[],"modifiers":["readonly"],"extended_attributes":[]},{"kind":"attribute","name":"pendingRemoteDescription","type_":"DOMString","arguments":[],"modifiers":["readonly"],"extended_attributes":[]},{"kind":"attribute","name":"privacyRequested","type_":"boolean","arguments":[],"modifiers":["readonly"],"extended_attributes":[]},{"kind":"attribute","name":"sctp","type_":"RTCSctpTransport?","arguments":[],"modifiers":["readonly"],"extended_attributes":[]},{"kind":"attribute","name":"signalingState","type_":"RTCSignalingState","arguments":[],"modifiers":["readonly"],"extended_attributes":[]},{"kind":"constructor","name":"","arguments":[],"modifiers":[],"extended_attributes":[]},{"kind":"operation","name":"addIceCandidate","type_":"undefined","arguments":[{"name":"candidate","type_":"DOMString","optional":false,"variadic":false,"extended_attributes":[]},{"name":"mid","type_":"DOMString","optional":false,"variadic":false,"extended_attributes":[]},{"name":"ufrag","type_":"DOMString","optional":false,"variadic":false,"extended_attributes":[]},{"name":"level","type_":"unsigned short?","optional":false,"variadic":false,"extended_attributes":[]}],"modifiers":[],"extended_attributes":["Throws"]},{"kind":"operation","name":"addTransceiver","type_":"RTCRtpTransceiver","arguments":[{"name":"init","type_":"RTCRtpTransceiverInit","optional":false,"variadic":false,"extended_attributes":[]},{"name":"kind","type_":"DOMString","optional":false,"variadic":false,"extended_attributes":[]},{"name":"sendTrack","type_":"MediaStreamTrack?","optional":false,"variadic":false,"extended_attributes":[]}],"modifiers":[],"extended_attributes":["Throws"]},{"kind":"operation","name":"chain","type_":"Promise<any>","arguments":[{"name":"op","type_":"ChainedOperation","optional":false,"variadic":false,"extended_attributes":[]}],"modifiers":[],"extended_attributes":["Throws"]},{"kind":"operation","name":"close","type_":"undefined","arguments":[],"modifiers":[],"extended_attributes":["Throws"]},{"kind":"operation","name":"closeStreams","type_":"undefined","arguments":[],"modifiers":[],"extended_attributes":["Throws"]},{"kind":"operation","name":"createAnswer","type_":"undefined","arguments":[],"modifiers":[],"extended_attributes":["Throws"]},{"kind":"operation","name":"createDataChannel","type_":"RTCDataChannel","arguments":[{"name":"label","type_":"DOMString","optional":false,"variadic":false,"extended_attributes":[]},{"name":"protocol","type_":"DOMString","optional":false,"variadic":false,"extended_attributes":[]},{"name":"type","type_":"unsigned short","optional":false,"variadic":false,"extended_attributes":[]},{"name":"ordered","type_":"boolean","optional":false,"variadic":false,"extended_attributes":[]},{"name":"maxTime","type_":"unsigned short","optional":false,"variadic":false,"extended_attributes":[]},{"name":"maxNum","type_":"unsigned short","optional":false,"variadic":false,"extended_attributes":[]},{"name":"externalNegotiated","type_":"boolean","optional":false,"variadic":false,"extended_attributes":[]},{"name":"stream","type_":"unsigned short","optional":false,"variadic":false,"extended_attributes":[]}],"modifiers":[],"extended_attributes":["Throws"]},{"kind":"operation","name":"createOffer","type_":"undefined","arguments":[{"name":"options","type_":"RTCOfferOptions","optional":true,"variadic":false,"default":"{}","extended_attributes":[]}],"modifiers":[],"extended_attributes":["Throws"]},{"kind":"operation","name":"createdSender","type_":"boolean","arguments":[{"name":"sender","type_":"RTCRtpSender","optional":false,"variadic":false,"extended_attributes":[]}],"modifiers":[],"extended_attributes":[]},{"kind":"operation","name":"disablePacketDump","type_":"undefined","arguments":[{"name":"level","type_":"unsigned long","optional":false,"variadic":false,"extended_attributes":[]},{"name":"type","type_":"mozPacketDumpType","optional":false,"variadic":false,"extended_attributes":[]},{"name":"sending","type_":"boolean","optional":false,"variadic":false,"extended_attributes":[]}],"modifiers":[],"extended_attributes":["Throws"]},{"kind":"operation","name":"enablePacketDump","type_":"undefined","arguments":[{"name":"level","type_":"unsigned long","optional":false,"variadic":false,"extended_attributes":[]},{"name":"type","type_":"mozPacketDumpType","optional":false,"variadic":false,"extended_attributes":[]},{"name":"sending","type_":"boolean","optional":false,"variadic":false,"extended_attributes":[]}],"modifiers":[],"extended_attributes":["Throws"]},{"kind":"operation","name":"getRemoteStreams","type_":"sequence<MediaStream>","arguments":[],"modifiers":[],"extended_attributes":[]},{"kind":"operation","name":"getStats","type_":"Promise<RTCStatsReport>","arguments":[{"name":"selector","type_":"MediaStreamTrack?","optional":false,"variadic":false,"extended_attributes":[]}],"modifiers":[],"extended_attributes":[]},{"kind":"operation","name":"getTransceivers","type_":"sequence<RTCRtpTransceiver>","arguments":[],"modifiers":[],"extended_attributes":[]},{"kind":"operation","name":"initialize","type_":"undefined","arguments":[{"name":"observer","type_":"PeerConnectionObserver","optional":false,"variadic":false,"extended_attributes":[]},{"name":"window","type_":"Window","optional":false,"variadic":false,"extended_attributes":[]}],"modifiers":[],"extended_attributes":["Throws"]},{"kind":"operation","name":"onSetDescriptionError","type_":"undefined","arguments":[],"modifiers":[],"extended_attributes":[]},{"kind":"operation","name":"onSetDescriptionSuccess","type_":"Promise<undefined>","arguments":[{"name":"type","type_":"RTCSdpType","optional":false,"variadic":false,"extended_attributes":[]},{"name":"remote","type_":"boolean","optional":false,"variadic":false,"extended_attributes":[]}],"modifiers":[],"extended_attributes":["Throws"]},{"kind":"operation","name":"pluginCrash","type_":"boolean","arguments":[{"name":"pluginId","type_":"unsigned long long","optional":false,"variadic":false,"extended_attributes":[]},{"name":"name","type_":"DOMString","optional":false,"variadic":false,"extended_attributes":[]}],"modifiers":[],"extended_attributes":[]},{"kind":"operation","name":"restartIce","type_":"undefined","arguments":[],"modifiers":[],"extended_attributes":[]},{"kind":"operation","name":"restartIceNoRenegotiationNeeded","type_":"undefined","arguments":[],"modifiers":[],"extended_attributes":[]},{"kind":"operation","name":"setConfiguration","type_":"undefined","arguments":[{"name":"config","type_":"RTCConfiguration","optional":true,"variadic":false,"default":"{}","extended_attributes":[]}],"modifiers":[],"extended_attributes":["Throws"]},{"kind":"operation","name":"setLocalDescription","type_":"undefined","arguments":[{"name":"action","type_":"long","optional":false,"variadic":false,"extended_attributes":[]},{"name":"sdp","type_":"DOMString","optional":false,"variadic":false,"extended_attributes":[]}],"modifiers":[],"extended_attributes":["Throws"]},{"kind":"operation","name":"setRemoteDescription","type_":"undefined","arguments":[{"name":"action","type_":"long","optional":false,"variadic":false,"extended_attributes":[]},{"name":"sdp","type_":"DOMString","optional":false,"variadic":false,"extended_attributes":[]}],"modifiers":[],"extended_attributes":["Throws"]},{"kind":"operation","name":"updateNegotiationNeeded","type_":"undefined","arguments":[],"modifiers":[],"extended_attributes":[]}]}