{"kind":"interface","name":"SVGPathSegCurvetoQuadraticAbs","inherits":"SVGPathSeg","extended_attributes":["Exposed=Window"],"members":[{"kind":"attribute","name":"x","type_":"unrestricted float","arguments":[],"modifiers":[],"extended_attributes":[]},{"kind":"attribute","name":"x1","type_":"unrestricted float","arguments":[],"modifiers":[],"extended_attributes":[]},{"kind":"attribute","name":"y","type_":"unrestricted float","arguments":[],"modifiers":[],"extended_attributes":[]},{"kind":"attribute","name":"y1","type_":"unrestricted float","arguments":[],"modifiers":[],"extended_attributes":[]}]}