{"kind":"interface","name":"RtcReceivedPacket","extended_attributes":["Exposed=(Window, Worker)","RuntimeEnabled=RTCRtpTransport"],"members":[{"kind":"attribute","name":"payloadByteLength","type_":"unsigned long","arguments":[],"modifiers":["readonly"],"extended_attributes":[]},{"kind":"attribute","name":"receiveTime","type_":"DOMHighResTimeStamp","arguments":[],"modifiers":["readonly"],"extended_attributes":[]},{"kind":"operation","name":"copyPayloadTo","type_":"void","arguments":[{"name":"destination","type_":"AllowSharedBufferSource","optional":false,"variadic":false,"extended_attributes":[]}],"modifiers":[],"extended_attributes":["RaisesException"]}]}