{"kind":"interface","name":"DocumentTransition","extended_attributes":["ActiveScriptWrappable","Exposed=Window","RuntimeEnabled=DocumentTransition"],"members":[{"kind":"attribute","name":"finished","type_":"Promise<void>","arguments":[],"modifiers":["readonly"],"extended_attributes":[]},{"kind":"operation","name":"abandon","type_":"void","arguments":[],"modifiers":[],"extended_attributes":["CallWith=ScriptState","RaisesException"]},{"kind":"operation","name":"prepare","type_":"Promise<void>","arguments":[{"name":"callback","type_":"DocumentTransitionCallback","optional":true,"variadic":false,"extended_attributes":[]}],"modifiers":[],"extended_attributes":["CallWith=ScriptState","RaisesException"]},{"kind":"operation","name":"start","type_":"Promise<void>","arguments":[{"name":"callback","type_":"DocumentTransitionCallback","optional":true,"variadic":false,"extended_attributes":[]}],"modifiers":[],"extended_attributes":["CallWith=ScriptState","RaisesException"]}]}