{"kind":"interface","name":"DeviceService","inherits":"EventTarget","extended_attributes":["ActiveScriptWrappable","Exposed=Window","RuntimeEnabled=DeviceInterface","SecureContext"],"members":[{"kind":"attribute","name":"onmanagedconfigurationchange","type_":"EventHandler","arguments":[],"modifiers":[],"extended_attributes":[]},{"kind":"operation","name":"getManagedConfiguration","type_":"Promise<object>","arguments":[{"name":"keys","type_":"sequence<DOMString>","optional":false,"variadic":false,"extended_attributes":[]}],"modifiers":[],"extended_attributes":["CallWith=ScriptState"]}]}