{"kind":"callback_interface","name":"UncaughtRejectionObserver","extended_attributes":[],"members":[{"kind":"operation","name":"onConsumed","type_":"void","arguments":[{"name":"p","type_":"Promise<any>","optional":false,"variadic":false,"extended_attributes":[]}],"modifiers":[],"extended_attributes":[]},{"kind":"operation","name":"onLeftUncaught","type_":"void","arguments":[{"name":"p","type_":"Promise<any>","optional":false,"variadic":false,"extended_attributes":[]}],"modifiers":[],"extended_attributes":[]}]}